{
  "results": [
    {
      "IDDiv": 1,
      "Place": "1",
      "Round": "F",
      "EventID": 17,
      "EventTypeID": 0,
      "ShortCode": "wOiDnxxioIlx0Rzsy",
      "disPlace": "1.",
      "disAthlete": "Doyle Steele",
      "disTeam": "San Diego",
      "Result": "25-03.25",
      "SortInt": 19696750,
      "AthleteID": 17565348,
      "FirstName": "Doyle",
      "LastName": "Steele",
      "Grade": "12",
      "TeamID": 1450,
      "SchoolName": "San Diego",
      "Gender": "M",
      "originalImperialSortInt": null
    },
    {
      "IDDiv": 1,
      "Place": "2",
      "Round": "F",
      "EventID": 17,
      "EventTypeID": 0,
      "ShortCode": "o3iZlXXijIZd6BxTe",
      "disPlace": "2.",
      "disAthlete": "Henry Harris",
      "disTeam": "Loyola",
      "Result": "24-07.25",
      "SortInt": 19704750,
      "AthleteID": 17180608,
      "FirstName": "Henry",
      "LastName": "Harris",
      "Grade": "12",
      "TeamID": 1747,
      "SchoolName": "Loyola",
      "Gender": "M",
      "originalImperialSortInt": null
    },
    {
      "IDDiv": 1,
      "Place": "3",
      "Round": "F",
      "EventID": 17,
      "EventTypeID": 0,
      "ShortCode": "wOiDnxxioIlxEQ1uy",
      "disPlace": "3.",
      "disAthlete": "Jerry Proctor",
      "disTeam": "Muir",
      "Result": "24-04.25",
      "SortInt": 19707750,
      "AthleteID": 17558756,
      "FirstName": "Jerry",
      "LastName": "Proctor",
      "Grade": "11",
      "TeamID": 1778,
      "SchoolName": "Muir",
      "Gender": "M",
      "originalImperialSortInt": null
    },
    {
      "IDDiv": 1,
      "Place": "4",
      "Round": "F",
      "EventID": 17,
      "EventTypeID": 0,
      "ShortCode": "4miPB00hmIRmKO4FZ",
      "disPlace": "4.",
      "disAthlete": "Mel Gray",
      "disTeam": "Montgomery",
      "Result": "24-04.25",
      "SortInt": 19707750,
      "AthleteID": 17558692,
      "FirstName": "Mel",
      "LastName": "Gray",
      "Grade": "11",
      "TeamID": 982,
      "SchoolName": "Montgomery",
      "Gender": "M",
      "originalImperialSortInt": null
    },
    {
      "IDDiv": 1,
      "Place": "5",
      "Round": "F",
      "EventID": 17,
      "EventTypeID": 0,
      "ShortCode": "wOiDnxxioIlxXA4Fy",
      "disPlace": "5.",
      "disAthlete": "Marion Anderson",
      "disTeam": "El Cerrito",
      "Result": "23-05.50",
      "SortInt": 19718500,
      "AthleteID": 17565142,
      "FirstName": "Marion",
      "LastName": "Anderson",
      "Grade": "12",
      "TeamID": 906,
      "SchoolName": "El Cerrito",
      "Gender": "M",
      "originalImperialSortInt": null
    },
    {
      "IDDiv": 1,
      "Place": "6",
      "Round": "F",
      "EventID": 17,
      "EventTypeID": 0,
      "ShortCode": "L6ijvBBUrIDaL5qhn",
      "disPlace": "6.",
      "disAthlete": "Jerry Garcia",
      "disTeam": "Roseville",
      "Result": "23-04.00",
      "SortInt": 19720000,
      "AthleteID": 17565320,
      "FirstName": "Jerry",
      "LastName": "Garcia",
      "Grade": "12",
      "TeamID": 822,
      "SchoolName": "Roseville",
      "Gender": "M",
      "originalImperialSortInt": null
    },
    {
      "IDDiv": 1,
      "Place": "7",
      "Round": "F",
      "EventID": 17,
      "EventTypeID": 0,
      "ShortCode": "W3iYD00ikIORBPYiZ",
      "disPlace": "7.",
      "disAthlete": "Lewis King",
      "disTeam": "Lincoln",
      "Result": "23-02.00",
      "SortInt": 19722000,
      "AthleteID": 17558553,
      "FirstName": "Lewis",
      "LastName": "King",
      "Grade": "11",
      "TeamID": 20373,
      "SchoolName": "Lincoln",
      "Gender": "M",
      "originalImperialSortInt": null
    }
  ]
}