{
  "results": [
    {
      "IDDiv": 1,
      "Place": "1",
      "Exhibition": false,
      "JD": false,
      "Round": "F",
      "pr": 0,
      "sr": 0,
      "EventID": 52,
      "PersonalEvent": true,
      "EventTypeID": 0,
      "SortIntRaw": 261120,
      "SortIntTemp": 261120,
      "ShortCode": "NVi2LxZTQ8H8xn0efd",
      "disPlace": "1.",
      "disGrade": "11",
      "disAthlete": "Elias Gedyon",
      "disTeam": "Loyola",
      "IDResult": 62284745,
      "Result": "4:21.12a",
      "SortInt": 261120,
      "Official": 1,
      "AthleteID": 12316330,
      "FirstName": "Elias",
      "LastName": "Gedyon",
      "Grade": "11",
      "AgeGrade": "11",
      "TeamID": 1747,
      "SchoolName": "Loyola",
      "Gender": "M",
      "EditorID": -168538,
      "hasSplitsSeries": false,
      "MediaCount": {},
      "originalImperialSortInt": null
    },
    {
      "IDDiv": 1,
      "Place": "2",
      "Exhibition": false,
      "JD": false,
      "Round": "F",
      "pr": 0,
      "sr": 0,
      "EventID": 52,
      "PersonalEvent": true,
      "EventTypeID": 0,
      "SortIntRaw": 261440,
      "SortIntTemp": 261440,
      "ShortCode": "XVix852tRpHMM4J1H8",
      "disPlace": "2.",
      "disGrade": "11",
      "disAthlete": "Ryan Urie",
      "disTeam": "Patrick Henry",
      "IDResult": 62284746,
      "Result": "4:21.44a",
      "SortInt": 261440,
      "Official": 1,
      "AthleteID": 3857906,
      "FirstName": "Ryan",
      "LastName": "Urie",
      "Grade": "11",
      "AgeGrade": "11",
      "TeamID": 1448,
      "SchoolName": "Patrick Henry",
      "Gender": "M",
      "EditorID": -168538,
      "hasSplitsSeries": false,
      "MediaCount": {},
      "originalImperialSortInt": null
    },
    {
      "IDDiv": 1,
      "Place": "3",
      "Exhibition": false,
      "JD": false,
      "Round": "F",
      "pr": 0,
      "sr": 0,
      "EventID": 52,
      "PersonalEvent": true,
      "EventTypeID": 0,
      "SortIntRaw": 261530,
      "SortIntTemp": 261530,
      "ShortCode": "W3ieN1dhl2HBvlyhZ",
      "disPlace": "3.",
      "disGrade": "12",
      "disAthlete": "Philip Macquitty",
      "disTeam": "Palo Alto",
      "IDResult": 62284747,
      "Result": "4:21.53a",
      "SortInt": 261530,
      "Official": 1,
      "AthleteID": 442710,
      "FirstName": "Philip",
      "LastName": "Macquitty",
      "Grade": "12",
      "AgeGrade": "12",
      "TeamID": 1093,
      "SchoolName": "Palo Alto",
      "Gender": "M",
      "EditorID": -168538,
      "hasSplitsSeries": false,
      "MediaCount": {},
      "originalImperialSortInt": null
    },
    {
      "IDDiv": 1,
      "Place": "4",
      "Exhibition": false,
      "JD": false,
      "Round": "F",
      "pr": 0,
      "sr": 0,
      "EventID": 52,
      "PersonalEvent": true,
      "EventTypeID": 0,
      "SortIntRaw": 261990,
      "SortIntTemp": 261990,
      "ShortCode": "P8iB56ASaZHly2wCl",
      "disPlace": "4.",
      "disGrade": "12",
      "disAthlete": "Erik Olson",
      "disTeam": "Novato",
      "IDResult": 62284748,
      "Result": "4:21.99a",
      "SortInt": 261990,
      "Official": 1,
      "AthleteID": 237951,
      "FirstName": "Erik",
      "LastName": "Olson",
      "Grade": "12",
      "AgeGrade": "12",
      "TeamID": 977,
      "SchoolName": "Novato",
      "Gender": "M",
      "EditorID": -168538,
      "hasSplitsSeries": false,
      "MediaCount": {},
      "originalImperialSortInt": null
    },
    {
      "IDDiv": 1,
      "Place": "5",
      "Exhibition": false,
      "JD": false,
      "Round": "F",
      "pr": 0,
      "sr": 0,
      "EventID": 52,
      "PersonalEvent": true,
      "EventTypeID": 0,
      "SortIntRaw": 262670,
      "SortIntTemp": 262670,
      "ShortCode": "x8ila3NhepHLmYaSN",
      "disPlace": "5.",
      "disGrade": "12",
      "disAthlete": "Germay Tesfani",
      "disTeam": "Hoover",
      "IDResult": 62284749,
      "Result": "4:22.67a",
      "SortInt": 262670,
      "Official": 1,
      "AthleteID": 185552,
      "FirstName": "Germay",
      "LastName": "Tesfani",
      "Grade": "12",
      "AgeGrade": "12",
      "TeamID": 1360,
      "SchoolName": "Hoover",
      "Gender": "M",
      "EditorID": -168538,
      "hasSplitsSeries": false,
      "MediaCount": {},
      "originalImperialSortInt": null
    },
    {
      "IDDiv": 1,
      "Place": "6",
      "Exhibition": false,
      "JD": false,
      "Round": "F",
      "pr": 0,
      "sr": 0,
      "EventID": 52,
      "PersonalEvent": true,
      "EventTypeID": 0,
      "SortIntRaw": 262980,
      "SortIntTemp": 262980,
      "ShortCode": "4mirWeyCM6HWjjrhZ",
      "disPlace": "6.",
      "disGrade": "12",
      "disAthlete": "Hugh Dowdy",
      "disTeam": "Petaluma",
      "IDResult": 62284750,
      "Result": "4:22.98a",
      "SortInt": 262980,
      "Official": 1,
      "AthleteID": 1531294,
      "FirstName": "Hugh",
      "LastName": "Dowdy",
      "Grade": "12",
      "AgeGrade": "12",
      "TeamID": 997,
      "SchoolName": "Petaluma",
      "Gender": "M",
      "EditorID": -168538,
      "hasSplitsSeries": false,
      "MediaCount": {},
      "originalImperialSortInt": null
    },
    {
      "IDDiv": 1,
      "Place": "7",
      "Exhibition": false,
      "JD": false,
      "Round": "F",
      "pr": 0,
      "sr": 0,
      "EventID": 52,
      "PersonalEvent": true,
      "EventTypeID": 0,
      "SortIntRaw": 263470,
      "SortIntTemp": 263470,
      "ShortCode": "x8ila3NhepHx1vKUN",
      "disPlace": "7.",
      "disGrade": "12",
      "disAthlete": "Travis Edwards",
      "disTeam": "Royal",
      "IDResult": 62284751,
      "Result": "4:23.47a",
      "SortInt": 263470,
      "Official": 1,
      "AthleteID": 694519,
      "FirstName": "Travis",
      "LastName": "Edwards",
      "Grade": "12",
      "AgeGrade": "12",
      "TeamID": 1852,
      "SchoolName": "Royal",
      "Gender": "M",
      "EditorID": -168538,
      "hasSplitsSeries": false,
      "MediaCount": {},
      "originalImperialSortInt": null
    },
    {
      "IDDiv": 1,
      "Place": "8",
      "Exhibition": false,
      "JD": false,
      "Round": "F",
      "pr": 0,
      "sr": 0,
      "EventID": 52,
      "PersonalEvent": true,
      "EventTypeID": 0,
      "SortIntRaw": 264400,
      "SortIntTemp": 264400,
      "ShortCode": "wOi5dXJuNVHY0Aety",
      "disPlace": "8.",
      "disGrade": "12",
      "disAthlete": "Javert Solorzano",
      "disTeam": "Granada Hills",
      "IDResult": 62284752,
      "Result": "4:24.40a",
      "SortInt": 264400,
      "Official": 1,
      "AthleteID": 104337,
      "FirstName": "Javert",
      "LastName": "Solorzano",
      "Grade": "12",
      "AgeGrade": "12",
      "TeamID": 1524,
      "SchoolName": "Granada Hills",
      "Gender": "M",
      "EditorID": -168538,
      "hasSplitsSeries": false,
      "MediaCount": {},
      "originalImperialSortInt": null
    },
    {
      "IDDiv": 1,
      "Place": "9",
      "Exhibition": false,
      "JD": false,
      "Round": "F",
      "pr": 0,
      "sr": 0,
      "EventID": 52,
      "PersonalEvent": true,
      "EventTypeID": 0,
      "SortIntRaw": 265250,
      "SortIntTemp": 265250,
      "ShortCode": "2KiLyPrUwKH585YCr",
      "disPlace": "9.",
      "disGrade": "12",
      "disAthlete": "Gustavo Mena",
      "disTeam": "Oxnard",
      "IDResult": 62284753,
      "Result": "4:25.25a",
      "SortInt": 265250,
      "Official": 1,
      "AthleteID": 1168014,
      "FirstName": "Gustavo",
      "LastName": "Mena",
      "Grade": "12",
      "AgeGrade": "12",
      "TeamID": 1809,
      "SchoolName": "Oxnard",
      "Gender": "M",
      "EditorID": -168538,
      "hasSplitsSeries": false,
      "MediaCount": {},
      "originalImperialSortInt": null
    },
    {
      "IDDiv": 1,
      "Place": "10",
      "Exhibition": false,
      "JD": false,
      "Round": "F",
      "pr": 0,
      "sr": 0,
      "EventID": 52,
      "PersonalEvent": true,
      "EventTypeID": 0,
      "SortIntRaw": 265650,
      "SortIntTemp": 265650,
      "ShortCode": "dvi03ORudaHqm0q8uz",
      "disPlace": "10.",
      "disGrade": "11",
      "disAthlete": "Justin Vilhauer",
      "disTeam": "Redwood (Visalia)",
      "IDResult": 62284754,
      "Result": "4:25.65a",
      "SortInt": 265650,
      "Official": 1,
      "AthleteID": 3813990,
      "FirstName": "Justin",
      "LastName": "Vilhauer",
      "Grade": "11",
      "AgeGrade": "11",
      "TeamID": 1355,
      "SchoolName": "Redwood (Visalia)",
      "Gender": "M",
      "EditorID": -168538,
      "hasSplitsSeries": false,
      "MediaCount": {},
      "originalImperialSortInt": null
    },
    {
      "IDDiv": 1,
      "Place": "11",
      "Exhibition": false,
      "JD": false,
      "Round": "F",
      "pr": 0,
      "sr": 0,
      "EventID": 52,
      "PersonalEvent": true,
      "EventTypeID": 0,
      "SortIntRaw": 265800,
      "SortIntTemp": 265800,
      "ShortCode": "W3ieN1dhl2HxolOfZ",
      "disPlace": "11.",
      "disGrade": "11",
      "disAthlete": "Chris Brewer",
      "disTeam": "Rancho Buena Vista",
      "IDResult": 62284755,
      "Result": "4:25.80a",
      "SortInt": 265800,
      "Official": 1,
      "AthleteID": 336208,
      "FirstName": "Chris",
      "LastName": "Brewer",
      "Grade": "11",
      "AgeGrade": "11",
      "TeamID": 1418,
      "SchoolName": "Rancho Buena Vista",
      "Gender": "M",
      "EditorID": -168538,
      "hasSplitsSeries": false,
      "MediaCount": {},
      "originalImperialSortInt": null
    },
    {
      "IDDiv": 1,
      "Place": "12",
      "Exhibition": false,
      "JD": false,
      "Round": "F",
      "pr": 0,
      "sr": 0,
      "EventID": 52,
      "PersonalEvent": true,
      "EventTypeID": 0,
      "SortIntRaw": 267430,
      "SortIntTemp": 267430,
      "ShortCode": "Jdind4JfKZHKE4EFA",
      "disPlace": "12.",
      "disGrade": "11",
      "disAthlete": "Robert Pflasterer",
      "disTeam": "Del Campo",
      "IDResult": 62284756,
      "Result": "4:27.43a",
      "SortInt": 267430,
      "Official": 1,
      "AthleteID": 520084,
      "FirstName": "Robert",
      "LastName": "Pflasterer",
      "Grade": "11",
      "AgeGrade": "11",
      "TeamID": 707,
      "SchoolName": "Del Campo",
      "Gender": "M",
      "EditorID": -168538,
      "hasSplitsSeries": false,
      "MediaCount": {},
      "originalImperialSortInt": null
    }
  ]
}