[
  {
    "place": 1,
    "country": "ROU",
    "mark": "6.96",
    "name": "Anișoara STANCIU-CUȘMIR"
  },
  {
    "place": 2,
    "country": "ROU",
    "mark": "6.81",
    "name": "Valy IONESCU"
  },
  {
    "place": 3,
    "country": "GBR",
    "mark": "6.80w",
    "name": "Susan HEARNSHAW"
  },
  {
    "place": 4,
    "country": "USA",
    "mark": "6.78w",
    "name": "Angela Elizabeth THACKER"
  },
  {
    "place": 5,
    "country": "USA",
    "mark": "6.77",
    "name": "Jackie JOYNER-KERSEE"
  },
  {
    "place": 6,
    "country": "AUS",
    "mark": "6.67",
    "name": "Robyn LORRAWAY"
  },
  {
    "place": 7,
    "country": "AUS",
    "mark": "6.53w",
    "name": "Glyniss Leanne NUNN-SAUNDERS-CEARNS"
  },
  {
    "place": 8,
    "country": "BAH",
    "mark": "6.44",
    "name": "Shonell FERGUSON"
  },
  {
    "place": 9,
    "country": "USA",
    "mark": "6.43",
    "name": "Carol Legrant LEWIS"
  },
  {
    "place": 10,
    "country": "JAM",
    "mark": "6.40",
    "name": "Dorothy SCOTT"
  },
  {
    "place": 11,
    "country": "AUS",
    "mark": "6.30",
    "name": "Linda GARDEN"
  },
  {
    "place": 12,
    "country": "YUG",
    "mark": "5.88",
    "name": "Snezana DANCETOVIC"
  },
  {
    "place": 13,
    "country": "NED",
    "mark": "Did not start",
    "name": "Catharina HIDDING"
  }
]