{
  "4A": {
    "4x200m": {
      "F": [
        {
          "id": "85517950",
          "eventCode": "4x200m",
          "gender": "F",
          "athleteId": "1501",
          "meetId": "315449",
          "teamId": "1097",
          "round": "f",
          "heat": "1",
          "place": "1",
          "windReading": "",
          "resultsDivisionId": null,
          "units": "99160",
          "teamName": "Atlanta",
          "firstName": "",
          "lastName": "",
          "gradYear": "0",
          "eventName": "4x200 Meter Relay",
          "eventDistance": "800",
          "ageGroupName": null,
          "meetName": "UIL Track and Field Championship",
          "videoId": 0,
          "divisionId": "12",
          "divisionName": "4A",
          "roundName": "Finals",
          "genderName": "Girls",
          "eventGenreOrder": 5,
          "teamProfileUrl": "http://tx.milesplit.com/teams/1097-atlanta",
          "teamLogo": "https://assets.sp.milesplit.com/team_logos/1097?v=1750534519",
          "profileUrl": "http://www.milesplit.com/athletes/1501",
          "performanceVideoId": null,
          "mark": "1:39.16"
        },
        {
          "id": "85517951",
          "eventCode": "4x200m",
          "gender": "F",
          "athleteId": "1501",
          "meetId": "315449",
          "teamId": "1675",
          "round": "f",
          "heat": "1",
          "place": "2",
          "windReading": "",
          "resultsDivisionId": null,
          "units": "99800",
          "teamName": null,
          "firstName": "",
          "lastName": "",
          "gradYear": "0",
          "eventName": "4x200 Meter Relay",
          "eventDistance": "800",
          "ageGroupName": null,
          "meetName": "UIL Track and Field Championship",
          "videoId": 0,
          "divisionId": "12",
          "divisionName": "4A",
          "roundName": "Finals",
          "genderName": "Girls",
          "eventGenreOrder": 5,
          "teamProfileUrl": "",
          "teamLogo": "https://assets.sp.milesplit.com/images/milesplit-favicon.png",
          "profileUrl": "http://www.milesplit.com/athletes/1501",
          "performanceVideoId": null,
          "mark": "1:39.80"
        },
        {
          "id": "85517952",
          "eventCode": "4x200m",
          "gender": "F",
          "athleteId": "1501",
          "meetId": "315449",
          "teamId": "868",
          "round": "f",
          "heat": "1",
          "place": "3",
          "windReading": "",
          "resultsDivisionId": null,
          "units": "100450",
          "teamName": "Dallas Carter",
          "firstName": "",
          "lastName": "",
          "gradYear": "0",
          "eventName": "4x200 Meter Relay",
          "eventDistance": "800",
          "ageGroupName": null,
          "meetName": "UIL Track and Field Championship",
          "videoId": 0,
          "divisionId": "12",
          "divisionName": "4A",
          "roundName": "Finals",
          "genderName": "Girls",
          "eventGenreOrder": 5,
          "teamProfileUrl": "http://tx.milesplit.com/teams/868-dallas-carter",
          "teamLogo": "https://assets.sp.milesplit.com/team_logos/868?v=1750534519",
          "profileUrl": "http://www.milesplit.com/athletes/1501",
          "performanceVideoId": null,
          "mark": "1:40.45"
        },
        {
          "id": "85517953",
          "eventCode": "4x200m",
          "gender": "F",
          "athleteId": "1501",
          "meetId": "315449",
          "teamId": "30495",
          "round": "f",
          "heat": "1",
          "place": "4",
          "windReading": "",
          "resultsDivisionId": null,
          "units": "102270",
          "teamName": "Waco La Vega",
          "firstName": "",
          "lastName": "",
          "gradYear": "0",
          "eventName": "4x200 Meter Relay",
          "eventDistance": "800",
          "ageGroupName": null,
          "meetName": "UIL Track and Field Championship",
          "videoId": 0,
          "divisionId": "12",
          "divisionName": "4A",
          "roundName": "Finals",
          "genderName": "Girls",
          "eventGenreOrder": 5,
          "teamProfileUrl": "http://tx.milesplit.com/teams/30495-waco-la-vega",
          "teamLogo": "https://assets.sp.milesplit.com/team_logos/30495?v=1750534519",
          "profileUrl": "http://www.milesplit.com/athletes/1501",
          "performanceVideoId": null,
          "mark": "1:42.27"
        },
        {
          "id": "85517954",
          "eventCode": "4x200m",
          "gender": "F",
          "athleteId": "1501",
          "meetId": "315449",
          "teamId": "1489",
          "round": "f",
          "heat": "1",
          "place": "5",
          "windReading": "",
          "resultsDivisionId": null,
          "units": "102660",
          "teamName": "Kilgore MS",
          "firstName": "",
          "lastName": "",
          "gradYear": "0",
          "eventName": "4x200 Meter Relay",
          "eventDistance": "800",
          "ageGroupName": null,
          "meetName": "UIL Track and Field Championship",
          "videoId": 0,
          "divisionId": "12",
          "divisionName": "4A",
          "roundName": "Finals",
          "genderName": "Girls",
          "eventGenreOrder": 5,
          "teamProfileUrl": "http://tx.milesplit.com/teams/1489-kilgore-ms",
          "teamLogo": "https://assets.sp.milesplit.com/team_logos/1489?v=1750534519",
          "profileUrl": "http://www.milesplit.com/athletes/1501",
          "performanceVideoId": null,
          "mark": "1:42.66"
        },
        {
          "id": "85517955",
          "eventCode": "4x200m",
          "gender": "F",
          "athleteId": "1501",
          "meetId": "315449",
          "teamId": "1604",
          "round": "f",
          "heat": "1",
          "place": "6",
          "windReading": "",
          "resultsDivisionId": null,
          "units": "103960",
          "teamName": "Graham",
          "firstName": "",
          "lastName": "",
          "gradYear": "0",
          "eventName": "4x200 Meter Relay",
          "eventDistance": "800",
          "ageGroupName": null,
          "meetName": "UIL Track and Field Championship",
          "videoId": 0,
          "divisionId": "12",
          "divisionName": "4A",
          "roundName": "Finals",
          "genderName": "Girls",
          "eventGenreOrder": 5,
          "teamProfileUrl": "http://tx.milesplit.com/teams/1604-graham",
          "teamLogo": "https://assets.sp.milesplit.com/team_logos/1604?v=1750534519",
          "profileUrl": "http://www.milesplit.com/athletes/1501",
          "performanceVideoId": null,
          "mark": "1:43.96"
        },
        {
          "id": "85517956",
          "eventCode": "4x200m",
          "gender": "F",
          "athleteId": "1501",
          "meetId": "315449",
          "teamId": "1606",
          "round": "f",
          "heat": "1",
          "place": "7",
          "windReading": "",
          "resultsDivisionId": null,
          "units": "104020",
          "teamName": "Vernon",
          "firstName": "",
          "lastName": "",
          "gradYear": "0",
          "eventName": "4x200 Meter Relay",
          "eventDistance": "800",
          "ageGroupName": null,
          "meetName": "UIL Track and Field Championship",
          "videoId": 0,
          "divisionId": "12",
          "divisionName": "4A",
          "roundName": "Finals",
          "genderName": "Girls",
          "eventGenreOrder": 5,
          "teamProfileUrl": "http://tx.milesplit.com/teams/1606-vernon",
          "teamLogo": "https://assets.sp.milesplit.com/team_logos/1606?v=1750534519",
          "profileUrl": "http://www.milesplit.com/athletes/1501",
          "performanceVideoId": null,
          "mark": "1:44.02"
        },
        {
          "id": "85517957",
          "eventCode": "4x200m",
          "gender": "F",
          "athleteId": "1501",
          "meetId": "315449",
          "teamId": "1726",
          "round": "f",
          "heat": "1",
          "place": "8",
          "windReading": "",
          "resultsDivisionId": null,
          "units": "104740",
          "teamName": "Wimberley",
          "firstName": "",
          "lastName": "",
          "gradYear": "0",
          "eventName": "4x200 Meter Relay",
          "eventDistance": "800",
          "ageGroupName": null,
          "meetName": "UIL Track and Field Championship",
          "videoId": 0,
          "divisionId": "12",
          "divisionName": "4A",
          "roundName": "Finals",
          "genderName": "Girls",
          "eventGenreOrder": 5,
          "teamProfileUrl": "http://tx.milesplit.com/teams/1726-wimberley",
          "teamLogo": "https://assets.sp.milesplit.com/team_logos/1726?v=1750534519",
          "profileUrl": "http://www.milesplit.com/athletes/1501",
          "performanceVideoId": null,
          "mark": "1:44.74"
        },
        {
          "id": "85517958",
          "eventCode": "4x200m",
          "gender": "F",
          "athleteId": "1501",
          "meetId": "315449",
          "teamId": "61799",
          "round": "f",
          "heat": "1",
          "place": "9",
          "windReading": "",
          "resultsDivisionId": null,
          "units": "104920",
          "teamName": "Cuero",
          "firstName": "",
          "lastName": "",
          "gradYear": "0",
          "eventName": "4x200 Meter Relay",
          "eventDistance": "800",
          "ageGroupName": null,
          "meetName": "UIL Track and Field Championship",
          "videoId": 0,
          "divisionId": "12",
          "divisionName": "4A",
          "roundName": "Finals",
          "genderName": "Girls",
          "eventGenreOrder": 5,
          "teamProfileUrl": "http://tx.milesplit.com/teams/61799-cuero",
          "teamLogo": "https://assets.sp.milesplit.com/team_logos/61799?v=1750534519",
          "profileUrl": "http://www.milesplit.com/athletes/1501",
          "performanceVideoId": null,
          "mark": "1:44.92"
        }
      ]
    }
  }
}