{
  "2A": {
    "300H": {
      "F": [
        {
          "id": "85591611",
          "eventCode": "300H",
          "gender": "F",
          "athleteId": "6826130",
          "meetId": "315449",
          "teamId": "1805",
          "round": "f",
          "heat": "1",
          "place": "1",
          "windReading": "",
          "resultsDivisionId": null,
          "units": "46460",
          "teamName": "Abernathy",
          "firstName": "Cheyann",
          "lastName": "Shadden",
          "gradYear": "2020",
          "eventName": "300 Meter Hurdles",
          "eventDistance": "300",
          "ageGroupName": null,
          "meetName": "UIL Track and Field Championship",
          "videoId": 0,
          "divisionId": "6",
          "divisionName": "2A",
          "roundName": "Finals",
          "genderName": "Girls",
          "eventGenreOrder": 3,
          "teamProfileUrl": "http://tx.milesplit.com/teams/1805-abernathy",
          "teamLogo": "https://assets.sp.milesplit.com/images/milesplit-favicon.png",
          "profileUrl": "http://www.milesplit.com/athletes/6826130-cheyann-shadden",
          "performanceVideoId": null,
          "mark": "46.46"
        },
        {
          "id": "85591612",
          "eventCode": "300H",
          "gender": "F",
          "athleteId": "5620324",
          "meetId": "315449",
          "teamId": "2085",
          "round": "f",
          "heat": "1",
          "place": "2",
          "windReading": "",
          "resultsDivisionId": null,
          "units": "46600",
          "teamName": "Chilton",
          "firstName": "Alivia",
          "lastName": "Waters",
          "gradYear": "2018",
          "eventName": "300 Meter Hurdles",
          "eventDistance": "300",
          "ageGroupName": null,
          "meetName": "UIL Track and Field Championship",
          "videoId": 0,
          "divisionId": "6",
          "divisionName": "2A",
          "roundName": "Finals",
          "genderName": "Girls",
          "eventGenreOrder": 3,
          "teamProfileUrl": "http://tx.milesplit.com/teams/2085-chilton",
          "teamLogo": "https://assets.sp.milesplit.com/team_logos/2085?v=1750534520",
          "profileUrl": "http://www.milesplit.com/athletes/5620324-alivia-waters",
          "performanceVideoId": null,
          "mark": "46.60"
        },
        {
          "id": "85591613",
          "eventCode": "300H",
          "gender": "F",
          "athleteId": "5896467",
          "meetId": "315449",
          "teamId": "1840",
          "round": "f",
          "heat": "1",
          "place": "3",
          "windReading": "",
          "resultsDivisionId": null,
          "units": "46620",
          "teamName": "San Saba",
          "firstName": "Ashlynn",
          "lastName": "Cash",
          "gradYear": "2019",
          "eventName": "300 Meter Hurdles",
          "eventDistance": "300",
          "ageGroupName": null,
          "meetName": "UIL Track and Field Championship",
          "videoId": 0,
          "divisionId": "6",
          "divisionName": "2A",
          "roundName": "Finals",
          "genderName": "Girls",
          "eventGenreOrder": 3,
          "teamProfileUrl": "http://tx.milesplit.com/teams/1840-san-saba",
          "teamLogo": "https://assets.sp.milesplit.com/team_logos/1840?v=1750534520",
          "profileUrl": "http://www.milesplit.com/athletes/5896467-ashlynn-cash",
          "performanceVideoId": null,
          "mark": "46.62"
        },
        {
          "id": "85591614",
          "eventCode": "300H",
          "gender": "F",
          "athleteId": "6930406",
          "meetId": "315449",
          "teamId": "46093",
          "round": "f",
          "heat": "1",
          "place": "4",
          "windReading": "",
          "resultsDivisionId": null,
          "units": "46660",
          "teamName": "Vega",
          "firstName": "Zoe",
          "lastName": "Webb",
          "gradYear": "2020",
          "eventName": "300 Meter Hurdles",
          "eventDistance": "300",
          "ageGroupName": null,
          "meetName": "UIL Track and Field Championship",
          "videoId": 0,
          "divisionId": "6",
          "divisionName": "2A",
          "roundName": "Finals",
          "genderName": "Girls",
          "eventGenreOrder": 3,
          "teamProfileUrl": "http://tx.milesplit.com/teams/46093-vega",
          "teamLogo": "https://assets.sp.milesplit.com/images/milesplit-favicon.png",
          "profileUrl": "http://www.milesplit.com/athletes/6930406-zoe-webb",
          "performanceVideoId": null,
          "mark": "46.66"
        },
        {
          "id": "85591615",
          "eventCode": "300H",
          "gender": "F",
          "athleteId": "5548330",
          "meetId": "315449",
          "teamId": "46598",
          "round": "f",
          "heat": "1",
          "place": "5",
          "windReading": "",
          "resultsDivisionId": null,
          "units": "47800",
          "teamName": "Lindsay ",
          "firstName": "Kayln",
          "lastName": "Pulte",
          "gradYear": "2018",
          "eventName": "300 Meter Hurdles",
          "eventDistance": "300",
          "ageGroupName": null,
          "meetName": "UIL Track and Field Championship",
          "videoId": 0,
          "divisionId": "6",
          "divisionName": "2A",
          "roundName": "Finals",
          "genderName": "Girls",
          "eventGenreOrder": 3,
          "teamProfileUrl": "http://tx.milesplit.com/teams/46598-lindsay",
          "teamLogo": "https://assets.sp.milesplit.com/team_logos/46598?v=1750534520",
          "profileUrl": "http://www.milesplit.com/athletes/5548330-kayln-pulte",
          "performanceVideoId": null,
          "mark": "47.80"
        },
        {
          "id": "85591616",
          "eventCode": "300H",
          "gender": "F",
          "athleteId": "6583719",
          "meetId": "315449",
          "teamId": "48837",
          "round": "f",
          "heat": "1",
          "place": "6",
          "windReading": "",
          "resultsDivisionId": null,
          "units": "47820",
          "teamName": "Post",
          "firstName": "Machala",
          "lastName": "Hingen",
          "gradYear": "2020",
          "eventName": "300 Meter Hurdles",
          "eventDistance": "300",
          "ageGroupName": null,
          "meetName": "UIL Track and Field Championship",
          "videoId": 0,
          "divisionId": "6",
          "divisionName": "2A",
          "roundName": "Finals",
          "genderName": "Girls",
          "eventGenreOrder": 3,
          "teamProfileUrl": "http://tx.milesplit.com/teams/48837-post",
          "teamLogo": "https://assets.sp.milesplit.com/images/milesplit-favicon.png",
          "profileUrl": "http://www.milesplit.com/athletes/6583719-machala-hingen",
          "performanceVideoId": null,
          "mark": "47.82"
        },
        {
          "id": "85591617",
          "eventCode": "300H",
          "gender": "F",
          "athleteId": "6222776",
          "meetId": "315449",
          "teamId": "46176",
          "round": "f",
          "heat": "1",
          "place": "7",
          "windReading": "",
          "resultsDivisionId": null,
          "units": "48090",
          "teamName": "Shiner",
          "firstName": "Bailey",
          "lastName": "Machacek",
          "gradYear": "2018",
          "eventName": "300 Meter Hurdles",
          "eventDistance": "300",
          "ageGroupName": null,
          "meetName": "UIL Track and Field Championship",
          "videoId": 0,
          "divisionId": "6",
          "divisionName": "2A",
          "roundName": "Finals",
          "genderName": "Girls",
          "eventGenreOrder": 3,
          "teamProfileUrl": "http://tx.milesplit.com/teams/46176-shiner",
          "teamLogo": "https://assets.sp.milesplit.com/team_logos/46176?v=1750534520",
          "profileUrl": "http://www.milesplit.com/athletes/6222776-bailey-machacek",
          "performanceVideoId": null,
          "mark": "48.09"
        },
        {
          "id": "85591618",
          "eventCode": "300H",
          "gender": "F",
          "athleteId": "6160333",
          "meetId": "315449",
          "teamId": "1904",
          "round": "f",
          "heat": "1",
          "place": "8",
          "windReading": "",
          "resultsDivisionId": null,
          "units": "49000",
          "teamName": null,
          "firstName": "Chesnee",
          "lastName": "Upshaw",
          "gradYear": "0",
          "eventName": "300 Meter Hurdles",
          "eventDistance": "300",
          "ageGroupName": null,
          "meetName": "UIL Track and Field Championship",
          "videoId": 0,
          "divisionId": "6",
          "divisionName": "2A",
          "roundName": "Finals",
          "genderName": "Girls",
          "eventGenreOrder": 3,
          "teamProfileUrl": "",
          "teamLogo": "https://assets.sp.milesplit.com/images/milesplit-favicon.png",
          "profileUrl": "http://www.milesplit.com/athletes/6160333-chesnee-upshaw",
          "performanceVideoId": null,
          "mark": "49.00"
        },
        {
          "id": "85591619",
          "eventCode": "300H",
          "gender": "F",
          "athleteId": "6525220",
          "meetId": "315449",
          "teamId": "1837",
          "round": "f",
          "heat": "1",
          "place": "9",
          "windReading": "",
          "resultsDivisionId": null,
          "units": "49100",
          "teamName": "Goldthwaite",
          "firstName": "Callie",
          "lastName": "Jernigan",
          "gradYear": "2020",
          "eventName": "300 Meter Hurdles",
          "eventDistance": "300",
          "ageGroupName": null,
          "meetName": "UIL Track and Field Championship",
          "videoId": 0,
          "divisionId": "6",
          "divisionName": "2A",
          "roundName": "Finals",
          "genderName": "Girls",
          "eventGenreOrder": 3,
          "teamProfileUrl": "http://tx.milesplit.com/teams/1837-goldthwaite",
          "teamLogo": "https://assets.sp.milesplit.com/team_logos/1837?v=1750534520",
          "profileUrl": "http://www.milesplit.com/athletes/6525220-callie-jernigan",
          "performanceVideoId": null,
          "mark": "49.10"
        }
      ]
    }
  }
}