[
  {
    "place": 1,
    "mark": "3:09.87",
    "name": null
  },
  {
    "place": 2,
    "mark": "3:10.21",
    "name": null
  },
  {
    "place": 3,
    "mark": "3:10.22",
    "name": null
  },
  {
    "place": 4,
    "mark": "3:10.36",
    "name": null
  },
  {
    "place": 5,
    "mark": "3:11.51",
    "name": null
  },
  {
    "place": 6,
    "mark": "3:12.07",
    "name": null
  },
  {
    "place": 7,
    "mark": "3:14.95",
    "name": null
  },
  {
    "place": 8,
    "mark": "3:15.04",
    "name": null
  },
  {
    "place": 9,
    "mark": "DQ",
    "name": null
  }
]